{
  "randomSeed" : 658898158,
  "resolution" : 1.0,
  "landBlur" : 30,
  "oceanEffectSize" : 30,
  "oceanEffect" : "Ripples",
  "worldSize" : 9000,
  "riverColor" : "76,76,76,255",
  "roadColor" : "0,0,0,255",
  "landBlurColor" : "234,234,245,255",
  "oceanEffectsColor" : "82,82,86,255",
  "coastlineColor" : "0,0,0,255",
  "centerLandToWaterProbability" : 1.0,
  "edgeLandToWaterProbability" : 0.0,
  "frayedBorder" : true,
  "frayedBorderColor" : "33,33,56,255",
  "frayedBorderBlurLevel" : 180,
  "grungeWidth" : 0,
  "generateBackground" : true,
  "generateBackgroundFromTexture" : false,
  "transparentBackground" : false,
  "colorizeOcean" : true,
  "colorizeLand" : true,
  "backgroundTextureImage" : "file:///Users/pgremo/Projects/nortantis/target/classes/assets/example%20textures/",
  "backgroundRandomSeed" : 1603542028,
  "oceanColor" : "140,144,168,255",
  "landColor" : "175,177,190,255",
  "generatedWidth" : 4096,
  "generatedHeight" : 2304,
  "fractalPower" : 1.3,
  "landBackgroundImage" : ".",
  "oceanBackgroundImage" : ".",
  "hueRange" : 16,
  "saturationRange" : 20,
  "brightnessRange" : 25,
  "drawText" : true,
  "alwaysCreateTextDrawerAndUpdateLandBackgroundWithOcean" : false,
  "textRandomSeed" : 658898158,
  "books" : [ "A Princess of Mars", "Ancient Egypt", "Jungle Tales of Tarzan" ],
  "titleFont" : "Herculanum 0 50",
  "regionFont" : "Herculanum 0 20",
  "mountainRangeFont" : "Herculanum 0 16",
  "otherMountainsFont" : "Herculanum 0 11",
  "riverFont" : "Herculanum 0 11",
  "boldBackgroundColor" : "234,234,245,255",
  "textColor" : "0,0,0,255",
  "edits" : {
    "text" : [ ],
    "centerEdits" : [ ],
    "regionEdits" : { },
    "hasIconEdits" : false,
    "edgeEdits" : [ ]
  },
  "drawBoldBackground" : true,
  "drawRegionColors" : false,
  "regionsRandomSeed" : 0,
  "drawBorder" : false,
  "borderType" : "dashes",
  "borderWidth" : 0,
  "frayedBorderSize" : 10000,
  "drawIcons" : true,
  "drawRivers" : true,
  "drawRoads" : true,
  "cityProbability" : 0.0,
  "lineStyle" : "Jagged",
  "cityIconSetName" : "middle ages",
  "pointPrecision" : 10.0
}